LICENSE
README.md
setup.cfg
setup.py
linkifile/LinkerClass.py
linkifile/__init__.py
linkifile/utils.py
linkifile.egg-info/PKG-INFO
linkifile.egg-info/SOURCES.txt
linkifile.egg-info/dependency_links.txt
linkifile.egg-info/requires.txt
linkifile.egg-info/top_level.txt