Metadata-Version: 2.1
Name: linkifile
Version: 0.1.3
Summary:  Empowering Effortless Data Linking.
Home-page: https://github.com/ar8372/linkifile
Author: Aman Kumar Raj
Author-email: ar837232342@gmail.com
Classifier: Programming Language :: Python :: 3
Classifier: License :: OSI Approved :: MIT License
Classifier: Operating System :: OS Independent
Requires-Python: >=3.6
License-File: LICENSE
